terminaltype/__init__.py
terminaltype/__main__.py
terminaltype/app.py
terminaltype/arguments.py
terminaltype/colors.py
terminaltype/history.py
terminaltype/keys.py
terminaltype/text.py
terminaltype/timer.py
terminaltype/utils.py
terminaltype/window.py
terminaltype/words/english1000
terminaltype/words/english200
terminaltype/words/italian1000
terminaltype/words/italian200
terminaltype/words/spanish1000
terminaltype/words/spanish200
terminaltype-0.0.3.dist-info/LICENSE
terminaltype-0.0.3.dist-info/METADATA
terminaltype-0.0.3.dist-info/WHEEL
terminaltype-0.0.3.dist-info/entry_points.txt
terminaltype-0.0.3.dist-info/top_level.txt
terminaltype-0.0.3.dist-info/RECORD
